copydata/__init__.py
copydata/__main__.py
copydata/cli.py
copydata-0.1.4.dist-info/licenses/LICENSE
copydata-0.1.4.dist-info/METADATA
copydata-0.1.4.dist-info/WHEEL
copydata-0.1.4.dist-info/entry_points.txt
copydata-0.1.4.dist-info/top_level.txt
copydata-0.1.4.dist-info/RECORD
